user_scanner/__init__.py
user_scanner/__main__.py
user_scanner/config.json
user_scanner/version.json
user_scanner/cli/__init__.py
user_scanner/cli/banner.py
user_scanner/core/__init__.py
user_scanner/core/email_orchestrator.py
user_scanner/core/formatter.py
user_scanner/core/helpers.py
user_scanner/core/orchestrator.py
user_scanner/core/result.py
user_scanner/core/version.py
user_scanner/email_scan/__init__.py
user_scanner/email_scan/adult/__init__.py
user_scanner/email_scan/adult/pornhub.py
user_scanner/email_scan/adult/sexvid.py
user_scanner/email_scan/adult/xnxx.py
user_scanner/email_scan/adult/xvideos.py
user_scanner/email_scan/community/__init__.py
user_scanner/email_scan/community/quora.py
user_scanner/email_scan/community/stackoverflow.py
user_scanner/email_scan/creator/__init__.py
user_scanner/email_scan/creator/gumroad.py
user_scanner/email_scan/creator/patreon.py
user_scanner/email_scan/dev/__init__.py
user_scanner/email_scan/dev/bitbucket.py
user_scanner/email_scan/dev/codecademy.py
user_scanner/email_scan/dev/codepen.py
user_scanner/email_scan/dev/devrant.py
user_scanner/email_scan/dev/github.py
user_scanner/email_scan/dev/huggingface.py
user_scanner/email_scan/dev/leetcode.py
user_scanner/email_scan/dev/replit.py
user_scanner/email_scan/dev/wordpress.py
user_scanner/email_scan/gaming/__init__.py
user_scanner/email_scan/gaming/chess_com.py
user_scanner/email_scan/hosting/__init__.py
user_scanner/email_scan/hosting/render.py
user_scanner/email_scan/learning/__init__.py
user_scanner/email_scan/learning/duolingo.py
user_scanner/email_scan/music/__init__.py
user_scanner/email_scan/music/lastfm.py
user_scanner/email_scan/music/spotify.py
user_scanner/email_scan/other/__init__.py
user_scanner/email_scan/other/eventbrite.py
user_scanner/email_scan/pipeline/__init__.py
user_scanner/email_scan/pipeline/axonaut.py
user_scanner/email_scan/pipeline/hubspot.py
user_scanner/email_scan/pipeline/insightly.py
user_scanner/email_scan/pipeline/zoho.py
user_scanner-1.1.0.6.dist-info/entry_points.txt
user_scanner-1.1.0.6.dist-info/licenses/LICENSE
user_scanner-1.1.0.6.dist-info/WHEEL
user_scanner-1.1.0.6.dist-info/METADATA
user_scanner-1.1.0.6.dist-info/RECORD
