Metadata-Version: 2.4
Name: user-scanner
Version: 1.1.0.6
Summary: Check username availability across multiple popular platforms
Keywords: username,checker,availability,social,tech,python,user-scanner
Author-email: Kaif <kafcodec@gmail.com>
Requires-Python: >=3.10
License-File: LICENSE
Requires-Dist: httpx[http2]>=0.27,<0.29
Requires-Dist: socksio>=1.0,<2
Requires-Dist: colorama>=0.4,<1
Project-URL: Homepage, https://github.com/kaifcodec/user-scanner
